tornado_resource_handler/__init__.py
tornado_resource_handler/tornado_resource_handler.py
tornado_resource_handler-0.1.3.dist-info/AUTHORS.rst
tornado_resource_handler-0.1.3.dist-info/LICENSE
tornado_resource_handler-0.1.3.dist-info/METADATA
tornado_resource_handler-0.1.3.dist-info/WHEEL
tornado_resource_handler-0.1.3.dist-info/top_level.txt
tornado_resource_handler-0.1.3.dist-info/RECORD
