Metadata-Version: 2.1
Name: tornado-resource-handler
Version: 0.1.3
Summary: Orgnize tornado handlers like resource
Home-page: https://github.com/louis-she/tornado_resource_handler
Author: Tornado Resource Handler
Author-email: chenglu.she@gmail.com
License: MIT license
Keywords: tornado_resource_handler
Platform: UNKNOWN
Classifier: Development Status :: 2 - Pre-Alpha
Classifier: Intended Audience :: Developers
Classifier: License :: OSI Approved :: MIT License
Classifier: Natural Language :: English
Classifier: Programming Language :: Python :: 3
Classifier: Programming Language :: Python :: 3.5
Classifier: Programming Language :: Python :: 3.6
Classifier: Programming Language :: Python :: 3.7
Classifier: Programming Language :: Python :: 3.8
Requires-Python: >=3.5
Requires-Dist: tornado
